aws_iam_utils/__init__.py
aws_iam_utils/action_data_overrides.py
aws_iam_utils/checks.py
aws_iam_utils/combiner.py
aws_iam_utils/constants.py
aws_iam_utils/generator.py
aws_iam_utils/policy.py
aws_iam_utils/policy_permission_item.py
aws_iam_utils/simplifier.py
aws_iam_utils/util.py
aws_iam_utils-1.8.0.dist-info/LICENSE
aws_iam_utils-1.8.0.dist-info/METADATA
aws_iam_utils-1.8.0.dist-info/WHEEL
aws_iam_utils-1.8.0.dist-info/top_level.txt
aws_iam_utils-1.8.0.dist-info/RECORD
