Metadata-Version: 2.1
Name: aws-iam-utils
Version: 1.8.0
Summary: AWS IAM utility library
Home-page: https://github.com/jtyers/aws-iam-utils
Author: Jonny Tyers
Author-email: jonny@jonnytyers.co.uk
License: MIT
Platform: UNKNOWN
Classifier: License :: OSI Approved :: MIT License
Classifier: Programming Language :: Python :: 3
Classifier: Programming Language :: Python :: 3.9
Classifier: Programming Language :: Python :: 3.10
License-File: LICENSE
Requires-Dist: policyuniverse (==1.5.0.20220523)
Requires-Dist: policy-sentry (==0.12.3)
